avro_to_markdown/__init__.py
avro_to_markdown/converter.py
tests/__init__.py
tests/unit/__init__.py
tests/unit/test_avro_to_markdown.py
avro_to_markdown-0.2.0.dist-info/LICENSE
avro_to_markdown-0.2.0.dist-info/METADATA
avro_to_markdown-0.2.0.dist-info/WHEEL
avro_to_markdown-0.2.0.dist-info/top_level.txt
avro_to_markdown-0.2.0.dist-info/RECORD
