Metadata-Version: 2.1
Name: avro-to-markdown
Version: 0.2.0
Summary: Create markdown documentation from an avro schema.
Home-page: UNKNOWN
Author: Colm O'Connor
Author-email: coconnor1@wayfair.com
License: See LICENSE
Platform: UNKNOWN
Classifier: Development Status :: 4 - Beta
Classifier: Programming Language :: Python
Classifier: Programming Language :: Python :: 3
Classifier: Programming Language :: Python :: 3.6
Classifier: Programming Language :: Python :: 3.7
Classifier: Programming Language :: Python :: 3.8
Classifier: Programming Language :: Python :: 3.9
Requires-Python: >=3.6
License-File: LICENSE
Requires-Dist: typing-extensions (~=3.7) ; python_version < "3.8"
